qzhub_core/__init__.py
qzhub_core/constants.py
qzhub_core/decorators.py
qzhub_core/exceptions.py
qzhub_core-0.1.1.dist-info/WHEEL
qzhub_core-0.1.1.dist-info/METADATA
qzhub_core-0.1.1.dist-info/RECORD
