Metadata-Version: 2.1
Name: qzhub-core
Version: 0.1.1
Summary: CORE Library for QZHub Team
Author: Aitemir Kuandyk
Author-email: mooniron.k@gmail.com
Requires-Python: >=3.6,<4.0
Classifier: Programming Language :: Python :: 3
Classifier: Programming Language :: Python :: 3.6
Classifier: Programming Language :: Python :: 3.7
Classifier: Programming Language :: Python :: 3.8
Classifier: Programming Language :: Python :: 3.9
